mdformat_rustfmt/__init__.py
mdformat_rustfmt-0.0.3.dist-info/entry_points.txt
mdformat_rustfmt-0.0.3.dist-info/LICENSE
mdformat_rustfmt-0.0.3.dist-info/WHEEL
mdformat_rustfmt-0.0.3.dist-info/METADATA
mdformat_rustfmt-0.0.3.dist-info/RECORD
